django_sabayon/__init__.py
django_sabayon/urls.py
django_sabayon/views.py
django_sabayon-0.1.1.dist-info/DESCRIPTION.rst
django_sabayon-0.1.1.dist-info/METADATA
django_sabayon-0.1.1.dist-info/RECORD
django_sabayon-0.1.1.dist-info/WHEEL
django_sabayon-0.1.1.dist-info/metadata.json
django_sabayon-0.1.1.dist-info/top_level.txt
