Metadata-Version: 2.0
Name: django-sabayon
Version: 0.1.1
Summary: Django support for https://github.com/dmathieu/sabayon
Home-page: https://github.com/w0de/django-sabayon
Author: w0de
Author-email: harry@sysop.ooo
License: UNKNOWN
Platform: UNKNOWN
